tests/__init__.py
tests/test_normalize_fragments.py
tests/test_normalize_netloc.py
tests/test_normalize_path.py
tests/test_normalize_query.py
tests/test_normalize_scheme.py
url_normalization/__init__.py
url_normalization/exceptions.py
url_normalization/url_normalization.py
UrlNormalization-0.1.0.dist-info/METADATA
UrlNormalization-0.1.0.dist-info/WHEEL
UrlNormalization-0.1.0.dist-info/top_level.txt
UrlNormalization-0.1.0.dist-info/RECORD
