Metadata-Version: 2.1
Name: UrlNormalization
Version: 0.1.0
Summary: Package for URL Nomalization.
Home-page: https://gitlab.com/witslb/url-normalization
Author: dwbruijn
License: UNKNOWN
Platform: UNKNOWN
Classifier: Programming Language :: Python :: 3
Classifier: License :: OSI Approved :: MIT License
Classifier: Operating System :: OS Independent
Requires-Python: >=3.7
Requires-Dist: idna (~=3.6)
Requires-Dist: validators (~=0.22.0)
